D FlipFlop/src/dut.v
module dff(
  input  wire clk,
  input  wire rst_n,   // active-low reset
  input  wire d,
  output reg  q
);
  always @(posedge clk or negedge rst_n) begin
    if (!rst_n) q <= 1'b0;
    else        q <= d;
  end
endmodule

D FlipFlop/src/tb_dut.v
`timescale 1ns/1ps
module tb;
  reg clk = 0;
  reg rst_n = 0;
  reg d = 0;
  wire q;

  dff u_dff(.clk(clk), .rst_n(rst_n), .d(d), .q(q));

  // clock: 10ns period -> 100 MHz
  always #5 clk = ~clk;

  initial begin
    $dumpfile("wave.vcd");
    $dumpvars(0, tb);

    // release reset
    #12 rst_n = 1;

    // stimulus
    #10 d = 1;
    #10 d = 0;
    #20 d = 1;
    #20 d = 0;
    #30 d = 1;

    #80 $finish;
  end
endmodule

D FlipFlop/wave.vcd
$date
	Sat Aug 23 11:06:20 2025
$end
$version
	Icarus Verilog
$end
$timescale
	1ps
$end
$scope module tb $end
$var wire 1 ! q $end
$var reg 1 " clk $end
$var reg 1 # d $end
$var reg 1 $ rst_n $end
$scope module u_dff $end
$var wire 1 " clk $end
$var wire 1 # d $end
$var wire 1 $ rst_n $end
$var reg 1 ! q $end
$upscope $end
$upscope $end
$enddefinitions $end
$comment Show the parameter values. $end
$dumpall
$end
#0
$dumpvars
0$
0#
0"
x!
$end
#5000
0!
1"
#10000
0"
#12000
1$
#15000
1"
#20000
0"
#22000
1#
#25000
1!
1"
#30000
0"
#32000
0#
#35000
0!
1"
#40000
0"
#45000
1"
#50000
0"
#52000
1#
#55000
1!
1"
#60000
0"
#65000
1"
#70000
0"
#72000
0#
#75000
0!
1"
#80000
0"
#85000
1"
#90000
0"
#95000
1"
#100000
0"
#102000
1#
#105000
1!
1"
