mod_10_Counter/src/dut.v

module tenCounter(input clk, reset, output reg[3:0] out);
  always @ (posedge clk) begin
    if (reset == 0)
      out <= 4'd0;
    else begin
      // count 0..9 then wrap to 0
      if (out == 4'd9)
        out <= 4'd0;
      else
        out <= out + 4'd1;
    end
  end
endmodule

mod_10_Counter/src/tb_dut.v

module tb;
  reg clk;
  reg reset;

  wire [3:0] out;

  tenCounter t10(clk, reset, out);

  always
    #5 clk = ~clk;

  initial begin
    // initialize signals at time 0 with sized values
    clk   = 1'b0;
    reset = 1'b0;

    $dumpfile("mod10_tb.vcd");
    $dumpvars(0, tb);
    #10 reset = 1'b1;
    #300 $finish;
  end

endmodule

mod_10_Counter/src/mod10_tb.vcd
$date
	Thu Nov 27 18:38:43 2025
$end
$version
	Icarus Verilog
$end
$timescale
	1s
$end
$scope module tb $end
$var wire 4 ! out [3:0] $end
$var reg 1 " clk $end
$var reg 1 # reset $end
$scope module t10 $end
$var wire 1 " clk $end
$var wire 1 # reset $end
$var reg 4 $ out [3:0] $end
$upscope $end
$upscope $end
$enddefinitions $end
$comment Show the parameter values. $end
$dumpall
$end
#0
$dumpvars
bx $
0#
0"
bx !
$end
#5
b0 !
b0 $
1"
#10
0"
1#
#15
b1 !
b1 $
1"
#20
0"
#25
b10 !
b10 $
1"
#30
0"
#35
b11 !
b11 $
1"
#40
0"
#45
b100 !
b100 $
1"
#50
0"
#55
b101 !
b101 $
1"
#60
0"
#65
b110 !
b110 $
1"
#70
0"
#75
b111 !
b111 $
1"
#80
0"
#85
b1000 !
b1000 $
1"
#90
0"
#95
b1001 !
b1001 $
1"
#100
0"
#105
b0 !
b0 $
1"
#110
0"
#115
b1 !
b1 $
1"
#120
0"
#125
b10 !
b10 $
1"
#130
0"
#135
b11 !
b11 $
1"
#140
0"
#145
b100 !
b100 $
1"
#150
0"
#155
b101 !
b101 $
1"
#160
0"
#165
b110 !
b110 $
1"
#170
0"
#175
b111 !
b111 $
1"
#180
0"
#185
b1000 !
b1000 $
1"
#190
0"
#195
b1001 !
b1001 $
1"
#200
0"
#205
b0 !
b0 $
1"
#210
0"
#215
b1 !
b1 $
1"
#220
0"
#225
b10 !
b10 $
1"
#230
0"
#235
b11 !
b11 $
1"
#240
0"
#245
b100 !
b100 $
1"
#250
0"
#255
b101 !
b101 $
1"
#260
0"
#265
b110 !
b110 $
1"
#270
0"
#275
b111 !
b111 $
1"
#280
0"
#285
b1000 !
b1000 $
1"
#290
0"
#295
b1001 !
b1001 $
1"
#300
0"
#305
b0 !
b0 $
1"
